piptegrator/__config__.py
piptegrator/__init__.py
piptegrator/common.py
piptegrator/helper.py
piptegrator/piptegrator.py
piptegrator-1.5.1.dist-info/LICENSE
piptegrator-1.5.1.dist-info/METADATA
piptegrator-1.5.1.dist-info/WHEEL
piptegrator-1.5.1.dist-info/entry_points.txt
piptegrator-1.5.1.dist-info/top_level.txt
piptegrator-1.5.1.dist-info/RECORD
