Metadata-Version: 2.1
Name: piptegrator
Version: 1.5.1
Summary: Piptegrator - Tools for managing requirements-driven projects
Home-page: https://github.com/MartinFalatic/piptegrator
Author: Martin F. Falatic
Author-email: martin@falatic.com
License: MIT License
Keywords: pip pip-compile pip-tools requirements uv
Classifier: Development Status :: 5 - Production/Stable
Classifier: Intended Audience :: Developers
Classifier: License :: OSI Approved :: MIT License
Classifier: Programming Language :: Python :: 3
Classifier: Programming Language :: Python :: 3.8
Classifier: Programming Language :: Python :: 3.9
Classifier: Programming Language :: Python :: 3.10
Classifier: Programming Language :: Python :: 3.11
Classifier: Programming Language :: Python :: 3.12
Classifier: Topic :: Utilities
License-File: LICENSE
Requires-Dist: pip-tools
Requires-Dist: requests
Requires-Dist: uv
